allianz_bonusdrive_client/__init__.py
allianz_bonusdrive_client/cli.py
allianz_bonusdrive_client/client.py
allianz_bonusdrive_client/print.py
allianz_bonusdrive_client/utils/__init__.py
allianz_bonusdrive_client/utils/constants.py
allianz_bonusdrive_client/utils/dataclasses.py
allianz_bonusdrive_client/utils/photon.py
allianz_bonusdrive_client-0.7.0.dist-info/WHEEL
allianz_bonusdrive_client-0.7.0.dist-info/METADATA
allianz_bonusdrive_client-0.7.0.dist-info/RECORD
