Metadata-Version: 2.3
Name: allianz-bonusdrive-client
Version: 0.7.0
Summary: A client for the Allianz BonusDrive program
Keywords: allianz,bonusdrive,telematics,api-client
Author-email: hello@xathon.de
License: MIT
Classifier: Development Status :: 4 - Beta
Classifier: License :: OSI Approved :: MIT License
Classifier: Programming Language :: Python :: 3.13
Classifier: Topic :: Software Development :: Libraries :: Python Modules
Requires-Dist: certifi>=2025.10.5
Requires-Dist: charset-normalizer>=3.4.0,<4.0.0
Requires-Dist: idna>=3.10,<4.0
Requires-Dist: polyline>=2.0.3,<3.0.0
Requires-Dist: requests>=2.32.0,<3.0.0
Requires-Dist: urllib3>=2.5.0,<3.0.0
Requires-Dist: colorama>=0.4.6,<1.0.0 ; extra == 'cli'
Requires-Dist: python-dotenv>=1.1.1 ; extra == 'cli'
Requires-Python: >=3.13
Project-URL: Homepage, https://github.com/xathon/Allianz-BonusDrive-Client
Project-URL: Issues, https://github.com/xathon/Allianz-BonusDrive-Client/issues
Project-URL: Repository, https://github.com/xathon/Allianz-BonusDrive-Client
Provides-Extra: cli
